example_package_RunningTrainsPlot/__init.py
example_package_RunningTrainsPlot/example.py
example_package_RunningTrainsPlot-0.0.1.dist-info/LICENSE
example_package_RunningTrainsPlot-0.0.1.dist-info/METADATA
example_package_RunningTrainsPlot-0.0.1.dist-info/WHEEL
example_package_RunningTrainsPlot-0.0.1.dist-info/top_level.txt
example_package_RunningTrainsPlot-0.0.1.dist-info/RECORD
