Metadata-Version: 2.1
Name: example_package_RunningTrainsPlot
Version: 0.0.1
Summary: A small example package about the RunningTrainsPlot
Author-email: ZeyuShen <sc22zs2@leeds.ac.uk>
Project-URL: Homepage, https://github.com/pypa/sampleproject
Project-URL: Issues, https://github.com/pypa/sampleproject/issues
Classifier: Programming Language :: Python :: 3
Classifier: License :: OSI Approved :: MIT License
Classifier: Operating System :: OS Independent
Requires-Python: >=3.8
License-File: LICENSE
